pythonlibupdate/__init__.py
pythonlibupdate/pylibupdator.py
pylibupdator-0.2.0.dist-info/LICENSE.txt
pylibupdator-0.2.0.dist-info/METADATA
pylibupdator-0.2.0.dist-info/WHEEL
pylibupdator-0.2.0.dist-info/entry_points.txt
pylibupdator-0.2.0.dist-info/top_level.txt
pylibupdator-0.2.0.dist-info/RECORD
