Metadata-Version: 2.1
Name: pylibupdator
Version: 0.2.0
Summary: A tool to check for newer versions of installed Python packages
Author: Dark Angel
Author-email: jrayvon@gmail.com
License-File: LICENSE.txt
Requires-Dist: requests
